structlint/__init__.py
structlint/checks.py
structlint/cli.py
structlint/collection.py
structlint/configuration.py
structlint/logic.py
structlint/regexes.py
structlint/reporting.py
structlint/utils.py
structlint-0.2.0.dist-info/WHEEL
structlint-0.2.0.dist-info/entry_points.txt
structlint-0.2.0.dist-info/METADATA
structlint-0.2.0.dist-info/RECORD
