Metadata-Version: 2.3
Name: structlint
Version: 0.2.0
Summary: Simple linter to enforce various aspects of source code structure.
Author: Isaac Riley
Author-email: Isaac Riley <yelircaasi@proton.me>
Requires-Dist: pydantic>=2.11
Requires-Dist: deal>4.24
Requires-Dist: multipledispatch>=1
Requires-Dist: grimp>=3.9
Requires-Dist: click>8
Requires-Python: >=3.11, <3.14
